{
  "project_info": {
    "project_number": "868022249417",
    "firebase_url": "https://tinder-f87cf-default-rtdb.firebaseio.com",
    "project_id": "tinder-f87cf",
    "storage_bucket": "tinder-f87cf.appspot.com"
  },
  "client": [
    {
      "client_info": {
        "mobilesdk_app_id": "1:868022249417:android:bfb93c2763742846d66a18",
        "android_client_info": {
          "package_name": "com.example.tinder"
        }
      },
      "oauth_client": [
        {
          "client_id": "868022249417-ko121o2ennd58cah080iim6e6l2it02g.apps.googleusercontent.com",
          "client_type": 3
        }
      ],
      "api_key": [
        {
          "current_key": "AIzaSyBTHC5-XNQjT92OtTfUmnfm-5aKDaYSEwI"
        }
      ],
      "services": {
        "appinvite_service": {
          "other_platform_oauth_client": [
            {
              "client_id": "868022249417-ko121o2ennd58cah080iim6e6l2it02g.apps.googleusercontent.com",
              "client_type": 3
            }
          ]
        }
      }
    },
    {
      "client_info": {
        "mobilesdk_app_id": "1:868022249417:android:9dce54e1cf86a323d66a18",
        "android_client_info": {
          "package_name": "com.example.useditemsapp"
        }
      },
      "oauth_client": [
        {
          "client_id": "868022249417-ko121o2ennd58cah080iim6e6l2it02g.apps.googleusercontent.com",
          "client_type": 3
        }
      ],
      "api_key": [
        {
          "current_key": "AIzaSyBTHC5-XNQjT92OtTfUmnfm-5aKDaYSEwI"
        }
      ],
      "services": {
        "appinvite_service": {
          "other_platform_oauth_client": [
            {
              "client_id": "868022249417-ko121o2ennd58cah080iim6e6l2it02g.apps.googleusercontent.com",
              "client_type": 3
            }
          ]
        }
      }
    }
  ],
  "configuration_version": "1"
}